MANIFEST.in
README.rst
setup.py
django_windows_tools/__init__.py
django_windows_tools/models.py
django_windows_tools/service.py
django_windows_tools/tests.py
django_windows_tools/views.py
django_windows_tools.egg-info/PKG-INFO
django_windows_tools.egg-info/SOURCES.txt
django_windows_tools.egg-info/dependency_links.txt
django_windows_tools.egg-info/entry_points.txt
django_windows_tools.egg-info/requires.txt
django_windows_tools.egg-info/top_level.txt
django_windows_tools/management/__init__.py
django_windows_tools/management/commands/__init__.py
django_windows_tools/management/commands/winfcgi.py
django_windows_tools/management/commands/winfcgi_install.py
django_windows_tools/management/commands/winservice_install.py
django_windows_tools/templates/windows_tools/iis/web.config
django_windows_tools/templates/windows_tools/service/service.ini
django_windows_tools/templates/windows_tools/service/service.py