Metadata-Version: 1.1
Name: django-windows-tools
Version: 0.2.1
Summary: Helper Management commands to host Django applications on Windows Servers.
Home-page: https://github.com/antoinemartin/django-windows-tools
Author: Antoine Martin
Author-email: antoine@openance.com
License: UNKNOWN
Keywords: Django Windows
Platform: UNKNOWN
Classifier: Development Status :: 4 - Beta
Classifier: Environment :: Web Environment
Classifier: Framework :: Django
Classifier: Operating System :: Microsoft :: Windows
Classifier: Intended Audience :: Developers
Classifier: License :: OSI Approved :: BSD License
Classifier: Operating System :: OS Independent
Classifier: Programming Language :: Python
Classifier: Topic :: Internet :: WWW/HTTP
Classifier: Topic :: System :: Installation/Setup
